pydna/__init__.py
pydna/_pretty.py
pydna/_thermodynamic_data.py
pydna/all.py
pydna/alphabet.py
pydna/amplicon.py
pydna/amplify.py
pydna/assembly.py
pydna/assembly2.py
pydna/codon.py
pydna/common_sub_strings.py
pydna/contig.py
pydna/cre_lox.py
pydna/crispr.py
pydna/design.py
pydna/dseq.py
pydna/dseqrecord.py
pydna/fakeseq.py
pydna/fusionpcr.py
pydna/gateway.py
pydna/gel.py
pydna/genbank.py
pydna/genbankfixer.py
pydna/ladders.py
pydna/oligonucleotide_hybridization.py
pydna/opencloning_models.py
pydna/parsers.py
pydna/primer.py
pydna/primer_screen.py
pydna/readers.py
pydna/seq.py
pydna/seqrecord.py
pydna/sequence_picker.py
pydna/sequence_regex.py
pydna/threading_timer_decorator_exit.py
pydna/tm.py
pydna/types.py
pydna/utils.py
pydna-5.5.6.dist-info/METADATA
pydna-5.5.6.dist-info/WHEEL
pydna-5.5.6.dist-info/licenses/LICENSE.txt
pydna-5.5.6.dist-info/RECORD
