Metadata-Version: 2.4
Name: pydna
Version: 5.5.6
Summary: Representing double stranded DNA and functions for simulating cloning and homologous recombination between DNA molecules.
License: BSD
License-File: LICENSE.txt
Author: Björn F. Johansson
Author-email: bjornjobb@gmail.com
Requires-Python: >=3.10,<4.0
Classifier: Development Status :: 4 - Beta
Classifier: Environment :: Console
Classifier: Intended Audience :: Education
Classifier: Intended Audience :: Developers
Classifier: Intended Audience :: Science/Research
Classifier: License :: OSI Approved :: BSD License
Classifier: Operating System :: OS Independent
Classifier: Programming Language :: Python :: 3.10
Classifier: Programming Language :: Python :: 3.11
Classifier: Programming Language :: Python :: 3.12
Classifier: Topic :: Education
Classifier: Topic :: Scientific/Engineering :: Bio-Informatics
Provides-Extra: clipboard
Provides-Extra: download
Provides-Extra: express
Provides-Extra: gel
Provides-Extra: primer-screen
Requires-Dist: appdirs (>=1.4.4)
Requires-Dist: biopython (==1.85)
Requires-Dist: cai2 (>=1.0.5) ; extra == "express"
Requires-Dist: matplotlib (>=3.4.3) ; extra == "gel"
Requires-Dist: networkx (>=2.8.8)
Requires-Dist: numpy (>1.26) ; python_version < "3.12"
Requires-Dist: numpy (>=2.3.0) ; python_version >= "3.12"
Requires-Dist: opencloning-linkml (>=0.4.9,<0.5.0)
Requires-Dist: pillow (>=8.4.0) ; extra == "gel"
Requires-Dist: prettytable (>=3.5.0)
Requires-Dist: pyahocorasick (>=2.2.0) ; extra == "primer-screen"
Requires-Dist: pydivsufsort (>=0.0.14)
Requires-Dist: pyfiglet (==0.8.post1)
Requires-Dist: pyparsing (>=2.4.7) ; extra == "download"
Requires-Dist: pyperclip (>=1.8.2) ; extra == "clipboard"
Requires-Dist: regex (>=2024.11.6,<2025.0.0)
Requires-Dist: requests (>=2.26.0) ; extra == "download"
Requires-Dist: scipy (>=1.11.3) ; (python_version >= "3.12") and (extra == "gel")
Requires-Dist: scipy (>=1.9.3) ; (python_version < "3.12") and (extra == "gel")
Requires-Dist: seguid (>=0.0.5)
Project-URL: Changelog, https://github.com/pydna-group/pydna/blob/master/docs/CHANGELOG.md#changelog
Project-URL: Documentation, https://pydna-group.github.io/pydna
Project-URL: Homepage, https://github.com/pydna-group/pydna#-pydna
Project-URL: Repository, https://github.com/pydna-group/pydna/tree/master
